client/__init__.py
client/client.py
client/client/__init__.py
client/client/add_contact.py
client/client/client_db.py
client/client/del_contact.py
client/client/main_window.py
client/client/main_window_conv.py
client/client/start_dialog.py
client/client/transport.py
client/common/__init__.py
client/common/decos_log.py
client/common/descripters.py
client/common/errors.py
client/common/metaclass.py
client/common/utils.py
client/common/variables.py
client/logs/__init__.py
client/logs/client_log_config.py
client/logs/server_log_config.py
my_first_py_messenger_client-0.0.1.dist-info/METADATA
my_first_py_messenger_client-0.0.1.dist-info/WHEEL
my_first_py_messenger_client-0.0.1.dist-info/top_level.txt
my_first_py_messenger_client-0.0.1.dist-info/RECORD
