Metadata-Version: 2.1
Name: my-first-py-messenger-client
Version: 0.0.1
Summary: Messenger Client
Home-page: UNKNOWN
Author: Aleksandr
Author-email: aleksander.17047665@gmail.com
License: UNKNOWN
Platform: UNKNOWN
Requires-Dist: PyQt5
Requires-Dist: sqlalchemy
Requires-Dist: pycryptodome
Requires-Dist: pycryptodomex
